covid19_outbreak_simulator/__init__.py
covid19_outbreak_simulator/cli.py
covid19_outbreak_simulator/event.py
covid19_outbreak_simulator/model.py
covid19_outbreak_simulator/plugin.py
covid19_outbreak_simulator/population.py
covid19_outbreak_simulator/report.py
covid19_outbreak_simulator/simulator.py
covid19_outbreak_simulator/utils.py
covid19_outbreak_simulator/plugins/__init__.py
covid19_outbreak_simulator/plugins/community.py
covid19_outbreak_simulator/plugins/community_infection.py
covid19_outbreak_simulator/plugins/community_spread.py
covid19_outbreak_simulator/plugins/contact_tracing.py
covid19_outbreak_simulator/plugins/init.py
covid19_outbreak_simulator/plugins/insert.py
covid19_outbreak_simulator/plugins/move.py
covid19_outbreak_simulator/plugins/pcrtest.py
covid19_outbreak_simulator/plugins/quarantine.py
covid19_outbreak_simulator/plugins/remove.py
covid19_outbreak_simulator/plugins/replace.py
covid19_outbreak_simulator/plugins/reset.py
covid19_outbreak_simulator/plugins/sample.py
covid19_outbreak_simulator/plugins/setparam.py
covid19_outbreak_simulator/plugins/stat.py
covid19_outbreak_simulator/plugins/swap.py
covid19_outbreak_simulator/plugins/testing.py
covid19_outbreak_simulator/plugins/vaccinate.py
covid19_outbreak_simulator-0.5.3.dist-info/LICENSE
covid19_outbreak_simulator-0.5.3.dist-info/METADATA
covid19_outbreak_simulator-0.5.3.dist-info/WHEEL
covid19_outbreak_simulator-0.5.3.dist-info/entry_points.txt
covid19_outbreak_simulator-0.5.3.dist-info/top_level.txt
covid19_outbreak_simulator-0.5.3.dist-info/RECORD
