Metadata-Version: 2.1
Name: covid19-outbreak-simulator
Version: 0.5.3
Summary: Population-based Forward-time Simulator for the Outbreak of COVID-19
Home-page: https://github.com/ictr/covid19-outbreak-simulator
Author: Bo Peng
Author-email: ben.bob@gmail.com
License: UNKNOWN
Keywords: covid19_outbreak_simulator
Platform: UNKNOWN
Classifier: Development Status :: 2 - Pre-Alpha
Classifier: Intended Audience :: Developers
Classifier: Natural Language :: English
Classifier: Programming Language :: Python :: 3
Classifier: Programming Language :: Python :: 3.6
Classifier: Programming Language :: Python :: 3.7
Classifier: Programming Language :: Python :: 3.8
Requires-Python: >=3.5
Requires-Dist: tqdm
Requires-Dist: numpy
Requires-Dist: scipy
